{
	"cmake" : 
	{
		"generator" : 
		{
			"multiConfig" : false,
			"name" : "Ninja"
		},
		"paths" : 
		{
			"cmake" : "C:/Program Files/JetBrains/CLion 2023.3.4/bin/cmake/win/x64/bin/cmake.exe",
			"cpack" : "C:/Program Files/JetBrains/CLion 2023.3.4/bin/cmake/win/x64/bin/cpack.exe",
			"ctest" : "C:/Program Files/JetBrains/CLion 2023.3.4/bin/cmake/win/x64/bin/ctest.exe",
			"root" : "C:/Program Files/JetBrains/CLion 2023.3.4/bin/cmake/win/x64/share/cmake-3.27"
		},
		"version" : 
		{
			"isDirty" : false,
			"major" : 3,
			"minor" : 27,
			"patch" : 8,
			"string" : "3.27.8",
			"suffix" : ""
		}
	},
	"objects" : 
	[
		{
			"jsonFile" : "codemodel-v2-8761334cc3772364be8a.json",
			"kind" : "codemodel",
			"version" : 
			{
				"major" : 2,
				"minor" : 6
			}
		},
		{
			"jsonFile" : "cache-v2-8ae1d82d094ce02529c8.json",
			"kind" : "cache",
			"version" : 
			{
				"major" : 2,
				"minor" : 0
			}
		},
		{
			"jsonFile" : "cmakeFiles-v1-b1912c9a4cee1de6a902.json",
			"kind" : "cmakeFiles",
			"version" : 
			{
				"major" : 1,
				"minor" : 0
			}
		},
		{
			"jsonFile" : "toolchains-v1-f1b2b3b9642b509dfa7c.json",
			"kind" : "toolchains",
			"version" : 
			{
				"major" : 1,
				"minor" : 0
			}
		}
	],
	"reply" : 
	{
		"cache-v2" : 
		{
			"jsonFile" : "cache-v2-8ae1d82d094ce02529c8.json",
			"kind" : "cache",
			"version" : 
			{
				"major" : 2,
				"minor" : 0
			}
		},
		"cmakeFiles-v1" : 
		{
			"jsonFile" : "cmakeFiles-v1-b1912c9a4cee1de6a902.json",
			"kind" : "cmakeFiles",
			"version" : 
			{
				"major" : 1,
				"minor" : 0
			}
		},
		"codemodel-v2" : 
		{
			"jsonFile" : "codemodel-v2-8761334cc3772364be8a.json",
			"kind" : "codemodel",
			"version" : 
			{
				"major" : 2,
				"minor" : 6
			}
		},
		"toolchains-v1" : 
		{
			"jsonFile" : "toolchains-v1-f1b2b3b9642b509dfa7c.json",
			"kind" : "toolchains",
			"version" : 
			{
				"major" : 1,
				"minor" : 0
			}
		}
	}
}
